alu.v
`timescale 1ns / 1ps

module alu #(parameter WORD_SIZE = 64) (input [WORD_SIZE - 1: 0] d1, input[WORD_SIZE - 1: 0] d2, input [3: 0] opcode, output [WORD_SIZE - 1: 0] out, output iszero, output iscarry);
    reg [WORD_SIZE - 1 : 0] outreg;
    reg carryreg;
    wire [WORD_SIZE - 1 : 0] d2_twoscomp;

    assign d2_twoscomp = (~d2) + 1;
    
    always @ *
    begin
        case(opcode)
            4'b0000:
            begin
                {carryreg, outreg} = d1 + d2;
            end
            4'b0001:
            begin
                {carryreg, outreg} = d1 + d2_twoscomp;
            end
            4'b0010:
            begin
                outreg = d1 * d2;
                carryreg = 1'b0;
            end
            4'b0011: 
            begin
                outreg = d1 | d2;
                carryreg = 1'b0;
            end
            4'b0100: 
            begin
                outreg = d1 & d2;
                carryreg = 1'b0;
            end
            4'b0101: 
            begin
                outreg = d1 ^ d2;
                carryreg = 1'b0;
            end
            4'b0110: 
            begin
                outreg = d1 ~| d2;
                carryreg = 1'b0;
            end
            4'b0111: 
            begin
                outreg = d1 ~& d2;
                carryreg = 1'b0;
            end
            4'b1000: 
            begin
                outreg = d1 ~^ d2;
                carryreg = 1'b0;
            end
            4'b1001: 
            begin
                outreg = d1 << d2;
                carryreg = 1'b0;
            end
            4'b1010: 
            begin
                outreg = d1 >> d2;
                carryreg = 1'b0;
            end
            default: 
            begin
                outreg = d1;
                carryreg = 1'b0;
            end
        endcase
    end

    assign out = outreg;
    assign iszero = (outreg == 1'b0);
    assign iscarry = carryreg;
endmodule

alu_tb.v
`include "alu.v"

module alu_tb;

parameter ALU_TEST_WORD_SIZE = 64;

reg [ALU_TEST_WORD_SIZE - 1:0] d1;
reg [ALU_TEST_WORD_SIZE - 1:0] d2;
reg [3:0] op;
wire [ALU_TEST_WORD_SIZE - 1:0] out;
wire iszero;
wire iscarry;

alu #(.WORD_SIZE(ALU_TEST_WORD_SIZE)) uut (d1, d2, op, out, iszero, iscarry);

initial begin
    $dumpfile("alu_tb.vcd");
    $dumpvars(0, alu_tb);
end

initial begin
    d1 = 64'd6; d2 = 64'd7; op = 4'b0000; #10;
    d1 = 64'd6; d2 = 64'd7; op = 4'b0001; #10;
    d1 = 64'd6; d2 = (~(64'd7)) + 64'd1; op = 4'b0000; #10;
    d1 = 64'd7; d2 = 64'd6; op = 4'b0001; #10;
    d1 = 64'd6; d2 = 64'd7; op = 4'b0010; #10;
    d1 = 64'b1011011; d2 = 64'b1100111; op = 4'b0100; #10; // AND, returns 67
    d1 = 64'b100001; d2 = 64'b1001; op = 4'b0011; #10; // OR, returns 41
    d1 = 64'b100001; d2 = 64'b1001; op = 4'b1111; #10; // INVALID, returns 33
    d1 = 64'b1100; d2 = 64'd2; op = 4'b1001; #10; // LEFT SHIFT, returns 48
    d1 = 64'b1100; d2 = 64'd2; op = 4'b1010; #10; // RIGHT SHIFT, returns 3
    d1 = 64'hFFFFFFFFFFFFFFFF; d2 = 64'h1; op = 4'b0000; #10;
end

endmodule

alu_tb.vcd
$date
	Thu Oct 30 23:52:32 2025
$end
$version
	Icarus Verilog
$end
$timescale
	1ps
$end
$scope module alu_tb $end
$var wire 64 ! out [63:0] $end
$var wire 1 " iszero $end
$var wire 1 # iscarry $end
$var parameter 32 $ ALU_TEST_WORD_SIZE $end
$var reg 64 % d1 [63:0] $end
$var reg 64 & d2 [63:0] $end
$var reg 4 ' op [3:0] $end
$scope module uut $end
$var wire 64 ( d1 [63:0] $end
$var wire 64 ) d2 [63:0] $end
$var wire 1 # iscarry $end
$var wire 4 * opcode [3:0] $end
$var wire 64 + out [63:0] $end
$var wire 1 " iszero $end
$var wire 64 , d2_twoscomp [63:0] $end
$var parameter 32 - WORD_SIZE $end
$var reg 1 . carryreg $end
$var reg 64 / outreg [63:0] $end
$upscope $end
$upscope $end
$enddefinitions $end
$comment Show the parameter values. $end
$dumpall
b1000000 -
b1000000 $
$end
#0
$dumpvars
b1101 /
0.
b1111111111111111111111111111111111111111111111111111111111111001 ,
b1101 +
b0 *
b111 )
b110 (
b0 '
b111 &
b110 %
0#
0"
b1101 !
$end
#10000
b1111111111111111111111111111111111111111111111111111111111111111 !
b1111111111111111111111111111111111111111111111111111111111111111 +
b1111111111111111111111111111111111111111111111111111111111111111 /
b1 '
b1 *
#20000
b111 ,
b0 '
b0 *
b1111111111111111111111111111111111111111111111111111111111111001 &
b1111111111111111111111111111111111111111111111111111111111111001 )
#30000
1#
1.
b1111111111111111111111111111111111111111111111111111111111111010 ,
b1 !
b1 +
b1 /
b1 '
b1 *
b110 &
b110 )
b111 %
b111 (
#40000
b1111111111111111111111111111111111111111111111111111111111111001 ,
0#
0.
b101010 !
b101010 +
b101010 /
b10 '
b10 *
b111 &
b111 )
b110 %
b110 (
#50000
b1111111111111111111111111111111111111111111111111111111110011001 ,
b1000011 !
b1000011 +
b1000011 /
b100 '
b100 *
b1100111 &
b1100111 )
b1011011 %
b1011011 (
#60000
b1111111111111111111111111111111111111111111111111111111111110111 ,
b101001 !
b101001 +
b101001 /
b11 '
b11 *
b1001 &
b1001 )
b100001 %
b100001 (
#70000
b100001 !
b100001 +
b100001 /
b1111 '
b1111 *
#80000
b1111111111111111111111111111111111111111111111111111111111111110 ,
b110000 !
b110000 +
b110000 /
b1001 '
b1001 *
b10 &
b10 )
b1100 %
b1100 (
#90000
b11 !
b11 +
b11 /
b1010 '
b1010 *
#100000
b1111111111111111111111111111111111111111111111111111111111111111 ,
1#
1.
1"
b0 !
b0 +
b0 /
b0 '
b0 *
b1 &
b1 )
b1111111111111111111111111111111111111111111111111111111111111111 %
b1111111111111111111111111111111111111111111111111111111111111111 (
