register_file.v
`timescale 1ns / 1ps

// A dual-read register file where each entry is 64 bits
// A synchronous, sequential circuit that activates on the positive edge of the clock
module register_file #(parameter WORD_SIZE = 64, REG_ADDR_SIZE = 4) (input clk, input en, input [REG_ADDR_SIZE - 1 : 0] write, input [REG_ADDR_SIZE - 1 : 0] r1, input [REG_ADDR_SIZE - 1 : 0] r2, input [WORD_SIZE - 1 : 0] data, output [WORD_SIZE - 1 : 0] out1, output [WORD_SIZE - 1 : 0] out2);
    reg [WORD_SIZE - 1 : 0] mem [0:(1 << REG_ADDR_SIZE) - 1];
    reg [WORD_SIZE - 1 : 0] out1reg;
    reg [WORD_SIZE - 1 : 0] out2reg;

    initial begin
        for(integer i = 0; i < (1 << REG_ADDR_SIZE); i = i + 1) begin
            mem[i] = 1'b0;
        end
        out1reg = 1'b0;
        out2reg = 1'b0;
    end
    
    always @(posedge clk)
    begin
        if(en)
        begin
            if(write > 1'b0)
                mem[write] <= data;
            mem[1'b0] <= 1'b0;
        end
        else
        begin
            out1reg <= 1'b0;
            out2reg <= 1'b0;
        end
    end

    always @(negedge clk)
    begin
        if(en)
        begin
            mem[1'b0] <= 1'b0;
            out1reg <= mem[r1];
            out2reg <= mem[r2];
        end
        else
        begin
            out1reg <= 1'b0;
            out2reg <= 1'b0;
        end
    end

    assign out1 = out1reg;
    assign out2 = out2reg;
endmodule

program_counter_old.v
`timescale 1ns / 1ps

module program_counter #(parameter INSTRUCTION_SIZE=16) (input clk, input [INSTRUCTION_SIZE - 1: 0] addr, output [INSTRUCTION_SIZE - 1 : 0] out);
    reg [INSTRUCTION_SIZE - 1 : 0] outreg;
    initial begin
        outreg = 1'b0;
    end

    always @ (posedge clk)
    begin
        outreg <= addr;
    end
    assign out = outreg;
endmodule

instruction_memory.v
`timescale 1ns / 1ps

module instruction_memory #(parameter INSTRUCTION_SIZE = 16, INSTRUCTION_ADDR_SIZE = 10) (input [INSTRUCTION_ADDR_SIZE - 1 : 0] addr, output [INSTRUCTION_SIZE - 1 : 0] out);
    reg [INSTRUCTION_SIZE - 1 : 0] mem [0:(1 << INSTRUCTION_ADDR_SIZE) - 1];
    reg [INSTRUCTION_SIZE - 1 : 0] outreg;
    
    initial begin
        outreg = 1'b0;

        for(integer i = 0; i < (1 << INSTRUCTION_ADDR_SIZE); i = i + 1) begin
            mem[i] = 1'b0;
        end

        /*================
        MACHINE CODE START
        ================*/

        /*
        Computes the nth fibonacci number
        LDI r1 1
        LDI r2 1
        LDI r4 4
        LDI r6 1
        ADD r1 r2 r3
        ADD r2 r0 r1
        ADD r3 r0 r2
        STR r0 r3 0
        SUB r4 r6 r4
        SUB r4 r0 r5
        BRH notzero 5
        MUL r1 r2 r5
        STR r0 r5 0
        HLT
        */

        mem[10'd0] = 16'h8101;
        mem[10'd1] = 16'h8201;
        mem[10'd2] = 16'h8440;
        mem[10'd3] = 16'h2123;
        mem[10'd4] = 16'h2201;
        mem[10'd5] = 16'h2302;
        mem[10'd6] = 16'hf030;
        mem[10'd7] = 16'h8f01;
        mem[10'd8] = 16'h34f4;
        mem[10'd9] = 16'h340f;
        mem[10'd10] = 16'hb003;
        mem[10'd11] = 16'h9125;
        mem[10'd12] = 16'h8f01;
        mem[10'd13] = 16'h25f5;
        mem[10'd14] = 16'hf050;
        mem[10'd15] = 16'h1000;

        /*==============
        MACHINE CODE END
        ==============*/
    end
    
    always @ *
    begin
        outreg = mem[addr];
    end

    assign out = outreg;
endmodule

call_stack.v
`timescale 1ns / 1ps

module call_stack #(parameter INSTRUCTION_ADDR_SIZE=10, parameter STACK_PTR_WIDTH=6) (input clk, input [INSTRUCTION_ADDR_SIZE - 1: 0] addr, input push, input en, output [INSTRUCTION_ADDR_SIZE - 1: 0] out);
    reg [INSTRUCTION_ADDR_SIZE - 1:0] stack[(1 << STACK_PTR_WIDTH) - 1:0];
    reg [STACK_PTR_WIDTH - 1:0] stackptr;

    assign out = stack[stackptr];

    initial begin
        stackptr = 6'b0;
        for(integer i = 0; i < (1 << STACK_PTR_WIDTH); i = i + 1) begin
            stack[i] = 1'b0;
        end
    end

    always @ (posedge clk)
    begin
        if(en)
        begin
            if(push)
            begin
                stack[stackptr + 1'b1] <= addr;
                stackptr <= stackptr + 1'b1;
            end
            else
            begin
                stackptr <= stackptr - 1'b1;
            end
        end
    end
endmodule

data_memory.v
`timescale 1ns / 1ps

// A dual-read memory file where each entry is 64 bits
// A synchronous, sequential circuit that activates on the positive edge of the clock
module data_memory #(parameter WORD_SIZE = 64, DATA_ADDR_SIZE = 8) (input clk, input [DATA_ADDR_SIZE - 1 : 0] addr, input [WORD_SIZE - 1 : 0] data, input write, input en, output [WORD_SIZE - 1 : 0] out, output [WORD_SIZE - 1 : 0] data_out);
    reg [WORD_SIZE - 1 : 0] mem [0:(1 << DATA_ADDR_SIZE) - 1];
    reg [WORD_SIZE - 1 : 0] outreg;

    assign data_out = mem[1'b0];

    initial begin
        outreg = 1'b0;
        for(integer i = 0; i < (1 << DATA_ADDR_SIZE); i = i + 1) begin
            mem[i] = 1'b0;
        end
    end
    
    always @(posedge clk)
    begin
        if(en)
        begin
            if(write)
                mem[addr] <= data;
            outreg <= mem[addr];
        end
        else
        begin
            outreg <= 1'b0;
        end
    end

    assign out = outreg;
endmodule

alu.v
`timescale 1ns / 1ps

module alu #(parameter WORD_SIZE = 64) (input [WORD_SIZE - 1: 0] d1, input[WORD_SIZE - 1: 0] d2, input [3: 0] opcode, output [WORD_SIZE - 1: 0] out, output iszero, output iscarry);
    reg [WORD_SIZE - 1 : 0] outreg;
    reg carryreg;
    wire [WORD_SIZE - 1 : 0] d2_twoscomp;

    assign d2_twoscomp = (~d2) + 1;
    
    always @ *
    begin
        case(opcode)
            4'b0000:
            begin
                {carryreg, outreg} = d1 + d2;
            end
            4'b0001:
            begin
                {carryreg, outreg} = d1 + d2_twoscomp;
            end
            4'b0010:
            begin
                outreg = d1 * d2;
                carryreg = 1'b0;
            end
            4'b0011: 
            begin
                outreg = d1 | d2;
                carryreg = 1'b0;
            end
            4'b0100: 
            begin
                outreg = d1 & d2;
                carryreg = 1'b0;
            end
            4'b0101: 
            begin
                outreg = d1 ^ d2;
                carryreg = 1'b0;
            end
            4'b0110: 
            begin
                outreg = d1 ~| d2;
                carryreg = 1'b0;
            end
            4'b0111: 
            begin
                outreg = d1 ~& d2;
                carryreg = 1'b0;
            end
            4'b1000: 
            begin
                outreg = d1 ~^ d2;
                carryreg = 1'b0;
            end
            4'b1001: 
            begin
                outreg = d1 << d2;
                carryreg = 1'b0;
            end
            4'b1010: 
            begin
                outreg = d1 >> d2;
                carryreg = 1'b0;
            end
            default: 
            begin
                outreg = d1;
                carryreg = 1'b0;
            end
        endcase
    end

    assign out = outreg;
    assign iszero = (outreg == 1'b0);
    assign iscarry = carryreg;
endmodule

computerold.v
`timescale 1ns / 1ps
`include "alu.v"
`include "call_stack.v"
`include "data_memory.v"
`include "instruction_memory.v"
`include "program_counter.v"
`include "register_file.v"

/*
Note to self.

TODO
1. For each input that's not just a direct connection, create a reg for it.
2. Determine the state transitions of the computer. Input these state transitions below
3. Test the code with a sample fibonacci program written in machine code
4. Write an assembler in python
*/
// A single-threaded computer with 1kb of RAM operating at a clock speed of 50MHz
// Why am I still doing this? T_T
module computer #(parameter WORD_SIZE = 64, DATA_ADDR_SIZE = 8, INSTRUCTION_ADDR_SIZE = 10, STACK_PTR_WIDTH = 6, REG_ADDR_SIZE = 4, CLOCK_HALF_PERIOD = 20, INSTRUCTION_SIZE = 16) (output [WORD_SIZE - 1:0] comp_output, output clk_out);
    /*
    module alu #(parameter WORD_SIZE = 64) (input [WORD_SIZE - 1: 0] d1, input[WORD_SIZE - 1: 0] d2, input [3: 0] opcode, output [WORD_SIZE - 1: 0] out, output iszero, output iscarry);
    module data_memory #(parameter WORD_SIZE = 64, DATA_ADDR_SIZE = 8) (input clk, input [DATA_ADDR_SIZE - 1 : 0] addr, input [WORD_SIZE - 1 : 0] data, input write, input en, output [WORD_SIZE - 1 : 0] out, output [WORD_SIZE - 1 : 0] data_out);
    module call_stack #(parameter INSTRUCTION_ADDR_SIZE=10, parameter STACK_PTR_WIDTH=6) (input clk, input [INSTRUCTION_ADDR_SIZE - 1: 0] addr, input push, input en, output [INSTRUCTION_ADDR_SIZE - 1: 0] out);
    module instruction_memory #(parameter INSTRUCTION_SIZE = 16, INSTRUCTION_ADDR_SIZE = 10) (input [INSTRUCTION_ADDR_SIZE - 1 : 0] addr, output [INSTRUCTION_SIZE - 1 : 0] out);
    module program_counter #(parameter INSTRUCTION_SIZE=16) (input clk, input [INSTRUCTION_SIZE - 1: 0] addr, output [INSTRUCTION_SIZE - 1 : 0] out);
    module register_file #(parameter WORD_SIZE = 64, REG_ADDR_SIZE = 4) (input clk, input en, input [REG_ADDR_SIZE - 1 : 0] write, input [REG_ADDR_SIZE - 1 : 0] r1, input [REG_ADDR_SIZE - 1 : 0] r2, input [WORD_SIZE - 1 : 0] data, output [WORD_SIZE - 1 : 0] out1, output [WORD_SIZE - 1 : 0] out2);
    */

    // Initializing the CPU
    initial begin
        alu_inp_2_reg = 1'b0;
        alu_inp_opcode_reg = 1'b0;
        d_mem_addr_reg = 1'b0;
        d_mem_data_reg = 1'b0;
        d_mem_write_reg = 1'b0;
        d_mem_en_reg = 1'b0;
        call_stack_addr_reg = 1'b0;
        call_stack_push_reg = 1'b0;
        call_stack_en_reg = 1'b0;
        pc_addr_reg = 1'b0;
        regfile_en_reg = 1'b0;
        regfile_write_reg = 1'b0;
        regfile_data_inp_reg = 1'b0;
        iszero_flag = 1'b0;
        iscarry_flag = 1'b0;

        #(3000); $finish;
    end

    // Dumping Vars
    initial begin
        $dumpfile("computer.vcd");
        $dumpvars(0, computer);
    end

    // Generating the Clock
    reg clk;
    reg clken;
    initial begin
        clk = 1'b0;
        clken = 1'b1;
        
        forever begin
            if(clken)
                #(CLOCK_HALF_PERIOD) clk = ~clk;
            else
                #(CLOCK_HALF_PERIOD) clk = 1'b0;
        end
    end

    // Defining Connections
    /// ALU Ports
    wire [WORD_SIZE - 1: 0] alu_inp_1;
    wire [WORD_SIZE - 1: 0] alu_inp_2;
    wire [3: 0] alu_inp_opcode;
    wire [WORD_SIZE - 1: 0] alu_out_res;
    wire alu_out_iszero;
    wire alu_out_iscarry;

    alu ALU (.d1(alu_inp_1), .d2(alu_inp_2), .opcode(alu_inp_opcode), .out(alu_out_res), .iszero(alu_out_iszero), .iscarry(alu_out_iscarry));

    //// ALU Inputs
    // reg [WORD_SIZE - 1: 0] alu_inp_1_reg;
    reg [WORD_SIZE - 1: 0] alu_inp_2_reg;
    reg [3: 0] alu_inp_opcode_reg;

    /// Data Memory Ports
    wire [DATA_ADDR_SIZE - 1 : 0] d_mem_addr;
    wire [WORD_SIZE - 1 : 0] d_mem_data;
    wire d_mem_write;
    wire d_mem_en;
    wire [WORD_SIZE - 1 : 0] d_mem_out_read;

    data_memory DATA_MEMORY (.clk(clk), .addr(d_mem_addr), .data(d_mem_data), .write(d_mem_write), .en(d_mem_en), .out(d_mem_out_read), .data_out(comp_output));
    
    //// Date Memory Inputs
    reg [DATA_ADDR_SIZE - 1 : 0] d_mem_addr_reg;
    reg [WORD_SIZE - 1 : 0] d_mem_data_reg;
    reg d_mem_write_reg;
    reg d_mem_en_reg;

    /// Call Stack Ports
    wire [INSTRUCTION_ADDR_SIZE - 1: 0] call_stack_addr;
    wire call_stack_push;
    wire call_stack_en;
    wire [INSTRUCTION_ADDR_SIZE - 1: 0] call_stack_out;
    call_stack CALL_STACK (.clk(clk), .addr(call_stack_addr), .push(push), .en(call_stack_en), .out(call_stack_out));
    
    //// Call Stack Inputs
    reg [INSTRUCTION_ADDR_SIZE - 1: 0] call_stack_addr_reg;
    reg call_stack_push_reg;
    reg call_stack_en_reg;

    /// Instruction Memory Ports
    wire [INSTRUCTION_ADDR_SIZE - 1 : 0] inst_mem_addr; // Already wired
    wire [INSTRUCTION_SIZE - 1 : 0] cur_inst; // ! Very important variable
    instruction_memory INSTRUCTION_MEMORY (.addr(inst_mem_addr), .out(cur_inst));
    
    /// Program Counter Ports
    wire [INSTRUCTION_SIZE - 1: 0] pc_addr;
    wire [INSTRUCTION_SIZE - 1: 0] pc_out;
    program_counter PROGRAM_COUNTER (.clk(clk), .addr(pc_addr), .out(pc_out));

    wire [INSTRUCTION_SIZE - 1: 0] pc_out_p1;
    assign pc_out_p1 = pc_out + 1'b1;

    //// Program Counter Inputs
    reg [INSTRUCTION_SIZE - 1: 0] pc_addr_reg;
    
    /// Register File Ports
    wire regfile_en;
    wire [REG_ADDR_SIZE - 1 : 0] regfile_write;
    wire [REG_ADDR_SIZE - 1 : 0] regfile_r1; // Already wired
    wire [REG_ADDR_SIZE - 1 : 0] regfile_r2; // Already wired
    wire [WORD_SIZE - 1 : 0] regfile_data_inp;
    wire [WORD_SIZE - 1 : 0] regfile_out1;
    wire [WORD_SIZE - 1 : 0] regfile_out2;
    register_file REGISTER_FILE (.clk(clk), .en(regfile_en), .write(regfile_write), .r1(regfile_r1), .r2(regfile_r2), .data(regfile_data_inp), .out1(regfile_out1), .out2(regfile_out2));

    //// Register File Inputs
    reg regfile_en_reg;
    reg [REG_ADDR_SIZE - 1 : 0] regfile_write_reg;
    reg [WORD_SIZE - 1 : 0] regfile_data_inp_reg;

    /// Assigning Registers
    // assign alu_inp_1 = alu_inp_1_reg;
    assign alu_inp_2 = alu_inp_2_reg;
    assign alu_inp_opcode = alu_inp_opcode_reg;
    assign d_mem_addr = d_mem_addr_reg;
    assign d_mem_data = d_mem_data_reg;
    assign d_mem_write = d_mem_write_reg;
    assign d_mem_en = d_mem_en_reg;
    assign call_stack_addr = call_stack_addr_reg;
    assign call_stack_push = call_stack_push_reg;
    assign call_stack_en = call_stack_en_reg;
    assign pc_addr = pc_addr_reg;
    assign regfile_en = regfile_en_reg;
    assign regfile_write = regfile_write_reg;
    assign regfile_data_inp = regfile_data_inp_reg;

    /// Permanent Connections
    assign alu_inp_1 = regfile_out1;
    assign inst_mem_addr = pc_out;
    assign regfile_r1 = cur_inst[11:8];
    assign regfile_r2 = cur_inst[7:4];

    wire [3:0] cur_inst_code;
    assign cur_inst_code = cur_inst[15:12];

    // Ports for the iscarry and iszero ALU flags
    reg iszero_flag;
    reg iscarry_flag;

    // Synchronous Block
    always@ (posedge clk) begin
        case(cur_inst_code)
            4'b0000: // NOP
            begin
                d_mem_en_reg <= 1'b0;
                call_stack_en_reg <= 1'b0;
                pc_addr_reg <= pc_out_p1;
                regfile_en_reg <= 1'b0;

                iszero_flag <= 1'b0;
                iscarry_flag <= 1'b0;
            end
            4'b0001: // HLT
            begin
                d_mem_en_reg <= 1'b0;
                call_stack_en_reg <= 1'b0;
                pc_addr_reg <= pc_out_p1;
                regfile_en_reg <= 1'b0;

                iszero_flag <= 1'b0;
                iscarry_flag <= 1'b0;
                
                clken <= 1'b0;
            end
            4'b0010: // ADD
            begin
                alu_inp_2_reg <= regfile_out2;
                alu_inp_opcode_reg <= 4'b0000;

                d_mem_en_reg <= 1'd0;
                
                call_stack_en_reg <= 1'd0;

                pc_addr_reg <= pc_out_p1;
                regfile_en_reg <= 1'b1;
                regfile_write_reg <= cur_inst[3:0];
                regfile_data_inp_reg <= alu_out_res;
                iszero_flag <= alu_out_iszero;
                iscarry_flag <= alu_out_iscarry;
            end
            4'b0011: // SUB
            begin
                alu_inp_2_reg <= regfile_out2;
                alu_inp_opcode_reg <= 4'b0001;

                d_mem_en_reg <= 1'd0;
                
                call_stack_en_reg <= 1'd0;

                pc_addr_reg <= pc_out_p1;

                regfile_en_reg <= 1'b1;
                regfile_write_reg <= cur_inst[3:0];
                regfile_data_inp_reg <= alu_out_res;

                iszero_flag <= alu_out_iszero;
                iscarry_flag <= alu_out_iscarry;
            end
            4'b0100: // NOR
            begin
                alu_inp_2_reg <= regfile_out2;
                alu_inp_opcode_reg <= 4'b0110;

                d_mem_en_reg <= 1'd0;
                
                call_stack_en_reg <= 1'd0;

                pc_addr_reg <= pc_out_p1;

                regfile_en_reg <= 1'b1;
                regfile_write_reg <= cur_inst[3:0];
                regfile_data_inp_reg <= alu_out_res;

                iszero_flag <= alu_out_iszero;
                iscarry_flag <= alu_out_iscarry;
            end
            4'b0101: // AND
            begin
                alu_inp_2_reg <= regfile_out2;
                alu_inp_opcode_reg <= 4'b0100;

                d_mem_en_reg <= 1'd0;
                
                call_stack_en_reg <= 1'd0;

                pc_addr_reg <= pc_out_p1;

                regfile_en_reg <= 1'b1;
                regfile_write_reg <= cur_inst[3:0];
                regfile_data_inp_reg <= alu_out_res;

                iszero_flag <= alu_out_iszero;
                iscarry_flag <= alu_out_iscarry;
            end
            4'b0110: // XOR
            begin
                alu_inp_2_reg <= regfile_out2;
                alu_inp_opcode_reg <= 4'b0101;

                d_mem_en_reg <= 1'd0;
                
                call_stack_en_reg <= 1'd0;

                pc_addr_reg <= pc_out_p1;

                regfile_en_reg <= 1'b1;
                regfile_write_reg <= cur_inst[3:0];
                regfile_data_inp_reg <= alu_out_res;

                iszero_flag <= alu_out_iszero;
                iscarry_flag <= alu_out_iscarry;
            end
            4'b0111: // RSH
            begin
                alu_inp_2_reg <= regfile_out2;
                alu_inp_opcode_reg <= 4'b1010;

                d_mem_en_reg <= 1'd0;
                
                call_stack_en_reg <= 1'd0;

                pc_addr_reg <= pc_out_p1;

                regfile_en_reg <= 1'b1;
                regfile_write_reg <= cur_inst[3:0];
                regfile_data_inp_reg <= alu_out_res;

                iszero_flag <= alu_out_iszero;
                iscarry_flag <= alu_out_iscarry;
            end
            4'b1000: // LDI
            begin
                d_mem_en_reg <= 1'b0;
                call_stack_en_reg <= 1'b0;

                pc_addr_reg <= pc_out_p1;

                regfile_en_reg <= 1'b1;
                regfile_write_reg <= cur_inst[11:8];
                regfile_data_inp_reg <= {56'd0, cur_inst[7:0]};

                iszero_flag <= 1'b0;
                iscarry_flag <= 1'b0;
            end
            4'b1001: // ADI
            begin
                alu_inp_2_reg <= {56'd0, cur_inst[7:0]};
                alu_inp_opcode_reg <= 4'd0000;

                d_mem_en_reg <= 1'd0;
                
                call_stack_en_reg <= 1'd0;

                pc_addr_reg <= pc_out_p1;

                regfile_en_reg <= 1'b1;
                regfile_write_reg <= cur_inst[11:8];
                regfile_data_inp_reg <= alu_out_res;

                iszero_flag <= alu_out_iszero;
                iscarry_flag <= alu_out_iscarry;
            end
            4'b1010: // JMP
            begin
                d_mem_en_reg <= 1'd0;
                
                call_stack_en_reg <= 1'd0;
                pc_addr_reg <= cur_inst[9:0];
                
                regfile_en_reg <= 1'b0;

                iszero_flag <= 1'b0;
                iscarry_flag <= 1'b0;
            end
            4'b1011: // BRH
            begin
                d_mem_en_reg <= 1'd0;
                
                call_stack_en_reg <= 1'd0;

                /*
                00 - not zero, 01 - zero, 10 - not carry, 11 - carry
                */
                if(cur_inst[11]) // check carry
                begin
                    pc_addr_reg = cur_inst[10] == iscarry_flag ? cur_inst[9:0] : pc_out_p1;
                end
                else // check carry
                begin
                    pc_addr_reg = cur_inst[10] == iszero_flag ? cur_inst[9:0] : pc_out_p1;
                end
                
                regfile_en_reg <= 1'b0;

                iszero_flag <= 1'b0;
                iscarry_flag <= 1'b0;
            end
            4'b1100: // CAL
            begin
                d_mem_en_reg <= 1'd0;
                
                call_stack_addr_reg <= pc_out_p1;
                call_stack_push_reg <= 1'b1;
                call_stack_en_reg <= 1'b1;
                pc_addr_reg <= cur_inst[9:0];
                
                regfile_en_reg <= 1'b0;

                iszero_flag <= 1'b0;
                iscarry_flag <= 1'b0;
            end
            4'b1101: // RET
            begin
                d_mem_en_reg <= 1'd0;
                
                call_stack_addr_reg <= 1'b0;
                call_stack_push_reg <= 1'b0;
                call_stack_en_reg <= 1'b1;
                pc_addr_reg <= call_stack_out;
                
                regfile_en_reg <= 1'b0;

                iszero_flag <= 1'b0;
                iscarry_flag <= 1'b0;
            end
            4'b1110: // LOD
            begin
                d_mem_addr_reg <= regfile_out1[DATA_ADDR_SIZE - 1:0] + {4'b0, cur_inst[3:0]};
                d_mem_data_reg <= 1'b0;
                d_mem_write_reg <= 1'b0;
                d_mem_en_reg <= 1'b1;

                call_stack_en_reg <= 1'b0;

                pc_addr_reg <= pc_out_p1;

                regfile_en_reg <= 1'b1;
                regfile_write_reg <= cur_inst[7:4];
                regfile_data_inp_reg <= d_mem_out_read;

                iszero_flag <= 1'b0;
                iscarry_flag <= 1'b0;
            end
            4'b1111: // STR
            begin
                pc_addr_reg <= pc_out_p1;
                d_mem_addr_reg <= regfile_out1[DATA_ADDR_SIZE - 1:0] + {4'b0, cur_inst[3:0]};
                d_mem_data_reg <= regfile_out2;
                d_mem_write_reg <= 1'b1;
                d_mem_en_reg <= 1'b1;
                
                call_stack_en_reg <= 1'b0;


                regfile_en_reg <= 1'b1;
                regfile_write_reg <= 1'b0;
                regfile_data_inp_reg <= 1'b0;

                iszero_flag <= 1'b0;
                iscarry_flag <= 1'b0;
            end
        endcase
    end

    // Connecting to External Ports
    assign clk_out = clk;
endmodule

computer.vcd
$date
	Mon Nov 03 01:26:06 2025
$end
$version
	Icarus Verilog
$end
$timescale
	1ps
$end
$scope module computer $end
$var wire 64 ! alu_inp_1 [63:0] $end
$var wire 4 " alu_inp_opcode [3:0] $end
$var wire 10 # call_stack_addr [9:0] $end
$var wire 1 $ call_stack_en $end
$var wire 1 % call_stack_push $end
$var wire 1 & clk_out $end
$var wire 8 ' d_mem_addr [7:0] $end
$var wire 64 ( d_mem_data [63:0] $end
$var wire 1 ) d_mem_en $end
$var wire 1 * d_mem_write $end
$var wire 16 + pc_addr [15:0] $end
$var wire 1 , push $end
$var wire 64 - regfile_data_inp [63:0] $end
$var wire 1 . regfile_en $end
$var wire 4 / regfile_write [3:0] $end
$var wire 4 0 regfile_r2 [3:0] $end
$var wire 4 1 regfile_r1 [3:0] $end
$var wire 64 2 regfile_out2 [63:0] $end
$var wire 64 3 regfile_out1 [63:0] $end
$var wire 16 4 pc_out_p1 [15:0] $end
$var wire 16 5 pc_out [15:0] $end
$var wire 10 6 inst_mem_addr [9:0] $end
$var wire 64 7 d_mem_out_read [63:0] $end
$var wire 4 8 cur_inst_code [3:0] $end
$var wire 16 9 cur_inst [15:0] $end
$var wire 64 : comp_output [63:0] $end
$var wire 10 ; call_stack_out [9:0] $end
$var wire 64 < alu_out_res [63:0] $end
$var wire 1 = alu_out_iszero $end
$var wire 1 > alu_out_iscarry $end
$var wire 64 ? alu_inp_2 [63:0] $end
$var parameter 32 @ CLOCK_HALF_PERIOD $end
$var parameter 32 A DATA_ADDR_SIZE $end
$var parameter 32 B INSTRUCTION_ADDR_SIZE $end
$var parameter 32 C INSTRUCTION_SIZE $end
$var parameter 32 D REG_ADDR_SIZE $end
$var parameter 32 E STACK_PTR_WIDTH $end
$var parameter 32 F WORD_SIZE $end
$var reg 64 G alu_inp_2_reg [63:0] $end
$var reg 4 H alu_inp_opcode_reg [3:0] $end
$var reg 10 I call_stack_addr_reg [9:0] $end
$var reg 1 J call_stack_en_reg $end
$var reg 1 K call_stack_push_reg $end
$var reg 1 L clk $end
$var reg 1 M clken $end
$var reg 8 N d_mem_addr_reg [7:0] $end
$var reg 64 O d_mem_data_reg [63:0] $end
$var reg 1 P d_mem_en_reg $end
$var reg 1 Q d_mem_write_reg $end
$var reg 1 R iscarry_flag $end
$var reg 1 S iszero_flag $end
$var reg 16 T pc_addr_reg [15:0] $end
$var reg 64 U regfile_data_inp_reg [63:0] $end
$var reg 1 V regfile_en_reg $end
$var reg 4 W regfile_write_reg [3:0] $end
$scope module ALU $end
$var wire 64 X d1 [63:0] $end
$var wire 64 Y d2 [63:0] $end
$var wire 1 > iscarry $end
$var wire 4 Z opcode [3:0] $end
$var wire 64 [ out [63:0] $end
$var wire 1 = iszero $end
$var wire 64 \ d2_twoscomp [63:0] $end
$var parameter 32 ] WORD_SIZE $end
$var reg 1 ^ carryreg $end
$var reg 64 _ outreg [63:0] $end
$upscope $end
$scope module CALL_STACK $end
$var wire 10 ` addr [9:0] $end
$var wire 1 L clk $end
$var wire 1 $ en $end
$var wire 10 a out [9:0] $end
$var wire 1 , push $end
$var parameter 32 b INSTRUCTION_ADDR_SIZE $end
$var parameter 32 c STACK_PTR_WIDTH $end
$var reg 6 d stackptr [5:0] $end
$scope begin $ivl_for_loop0 $end
$var integer 32 e i [31:0] $end
$upscope $end
$upscope $end
$scope module DATA_MEMORY $end
$var wire 8 f addr [7:0] $end
$var wire 1 L clk $end
$var wire 64 g data [63:0] $end
$var wire 64 h data_out [63:0] $end
$var wire 1 ) en $end
$var wire 64 i out [63:0] $end
$var wire 1 * write $end
$var parameter 32 j DATA_ADDR_SIZE $end
$var parameter 32 k WORD_SIZE $end
$var reg 64 l outreg [63:0] $end
$scope begin $ivl_for_loop1 $end
$var integer 32 m i [31:0] $end
$upscope $end
$upscope $end
$scope module INSTRUCTION_MEMORY $end
$var wire 10 n addr [9:0] $end
$var wire 16 o out [15:0] $end
$var parameter 32 p INSTRUCTION_ADDR_SIZE $end
$var parameter 32 q INSTRUCTION_SIZE $end
$var reg 16 r outreg [15:0] $end
$scope begin $ivl_for_loop2 $end
$var integer 32 s i [31:0] $end
$upscope $end
$upscope $end
$scope module PROGRAM_COUNTER $end
$var wire 16 t addr [15:0] $end
$var wire 1 L clk $end
$var wire 16 u out [15:0] $end
$var parameter 32 v INSTRUCTION_SIZE $end
$var reg 16 w outreg [15:0] $end
$upscope $end
$scope module REGISTER_FILE $end
$var wire 1 L clk $end
$var wire 64 x data [63:0] $end
$var wire 1 . en $end
$var wire 64 y out2 [63:0] $end
$var wire 4 z r1 [3:0] $end
$var wire 4 { r2 [3:0] $end
$var wire 4 | write [3:0] $end
$var wire 64 } out1 [63:0] $end
$var parameter 32 ~ REG_ADDR_SIZE $end
$var parameter 32 !" WORD_SIZE $end
$var reg 64 "" out1reg [63:0] $end
$var reg 64 #" out2reg [63:0] $end
$scope begin $ivl_for_loop3 $end
$var integer 32 $" i [31:0] $end
$upscope $end
$upscope $end
$upscope $end
$enddefinitions $end
$comment Show the parameter values. $end
$dumpall
b1000000 !"
b100 ~
b10000 v
b10000 q
b1010 p
b1000000 k
b1000 j
b110 c
b1010 b
b1000000 ]
b1000000 F
b110 E
b100 D
b10000 C
b1010 B
b1000 A
b1 @
$end
#0
$dumpvars
b10000 $"
b0 #"
b0 ""
b0 }
b1 |
b0 {
b1 z
b0 y
b1 x
b0 w
b0 u
b1 t
b10000000000 s
b1000000100000001 r
b1000000100000001 o
b0 n
b100000000 m
b0 l
b0 i
b0 h
b0 g
b0 f
b1000000 e
b0 d
b0 a
b0 `
b0 _
0^
b0 \
b0 [
b0 Z
b0 Y
b0 X
b1 W
1V
b1 U
b1 T
0S
0R
0Q
0P
b0 O
b0 N
1M
1L
0K
0J
b0 I
b0 H
b0 G
b0 ?
0>
1=
b0 <
b0 ;
b0 :
b1000000100000001 9
b1000 8
b0 7
b0 6
b0 5
b1 4
b0 3
b0 2
b1 1
b0 0
b1 /
1.
b1 -
z,
b1 +
0*
0)
b0 (
b0 '
1&
0%
0$
b0 #
b0 "
b0 !
$end
#1000
0&
0L
#2000
b10 1
b10 z
b10 /
b10 |
b10 W
b1000001000000001 9
b1000001000000001 o
b1000001000000001 r
b1 6
b1 n
b10 +
b10 t
b10 T
b10 4
b1 5
b1 u
b1 w
1&
1L
#3000
0&
0L
#4000
b100 0
b100 {
b100 1
b100 z
b1000000 -
b1000000 x
b1000000 U
b100 /
b100 |
b100 W
b1000010001000000 9
b1000010001000000 o
b1000010001000000 r
b10 6
b10 n
b11 +
b11 t
b11 T
b11 4
b10 5
b10 u
b10 w
1&
1L
#5000
0&
0L
#6000
b10 8
b10 0
b10 {
b1 1
b1 z
b0 -
b0 x
b0 U
b11 /
b11 |
b11 W
b10000100100011 9
b10000100100011 o
b10000100100011 r
b11 6
b11 n
b100 +
b100 t
b100 T
b100 4
b11 5
b11 u
b11 w
1&
1L
#7000
b1111111111111111111111111111111111111111111111111111111111111111 \
b10 -
b10 x
b10 U
b1 ?
b1 G
b1 Y
0=
b10 <
b10 [
b10 _
b1 2
b1 y
b1 #"
b1 !
b1 X
b1 3
b1 }
b1 ""
0&
0L
#8000
b0 0
b0 {
b10 1
b10 z
b1 /
b1 |
b1 W
b10001000000001 9
b10001000000001 o
b10001000000001 r
b100 6
b100 n
b101 +
b101 t
b101 T
b101 4
b100 5
b100 u
b100 w
1&
1L
#9000
b1 -
b1 x
b1 U
b0 \
b1 <
b1 [
b1 _
b0 ?
b0 G
b0 Y
b0 2
b0 y
b0 #"
0&
0L
#10000
b11 1
b11 z
b10 /
b10 |
b10 W
b10001100000010 9
b10001100000010 o
b10001100000010 r
b101 6
b101 n
b110 +
b110 t
b110 T
b110 4
b101 5
b101 u
b101 w
1&
1L
#11000
b10 -
b10 x
b10 U
b10 <
b10 [
b10 _
b10 !
b10 X
b10 3
b10 }
b10 ""
0&
0L
#12000
b0 -
b0 x
b0 U
1)
1P
1*
1Q
b10 '
b10 f
b10 N
b1111 8
b11 0
b11 {
b0 1
b0 z
b0 /
b0 |
b0 W
b1111000000110000 9
b1111000000110000 o
b1111000000110000 r
b110 6
b110 n
b111 +
b111 t
b111 T
b111 4
b110 5
b110 u
b110 w
1&
1L
#13000
b10 (
b10 g
b10 O
b0 '
b0 f
b0 N
1=
b0 <
b0 [
b0 _
b10 2
b10 y
b10 #"
b0 !
b0 X
b0 3
b0 }
b0 ""
0&
0L
